wv/__init__.py
wv-0.0.6.dist-info/licenses/LICENSE
wv-0.0.6.dist-info/METADATA
wv-0.0.6.dist-info/WHEEL
wv-0.0.6.dist-info/top_level.txt
wv-0.0.6.dist-info/RECORD
