Metadata-Version: 2.4
Name: wv
Version: 0.0.6
Summary: Weighted Principal Component Analysis using Expectation Maximization
Home-page: https://github.com/t-c-w/wv
Author: Thor Whalen
License: apache-2.0
Platform: any
License-File: LICENSE
Dynamic: license-file
